LICENSE
MANIFEST.in
README.md
setup.py
tox.ini
Flask_Plugins.egg-info/PKG-INFO
Flask_Plugins.egg-info/SOURCES.txt
Flask_Plugins.egg-info/dependency_links.txt
Flask_Plugins.egg-info/not-zip-safe
Flask_Plugins.egg-info/requires.txt
Flask_Plugins.egg-info/top_level.txt
flask_plugins/__init__.py
flask_plugins/_compat.py
tests/__init__.py
tests/eventmanager_tests.py
tests/plugin_tests.py
tests/pluginmanager_tests.py
tests/plugins/__init__.py
tests/plugins/test1/__init__.py
tests/plugins/test2/__init__.py
tests/plugins/test3/__init__.py
tests/plugs/__init__.py
tests/plugs/wrong/__init__.py