Metadata-Version: 1.1
Name: Flask-Plugins
Version: 1.6.0
Summary: Create plugins for your Flask application
Home-page: https://github.com/sh4nks/flask-plugins
Author: Peter Justin
Author-email: peter.justin@outlook.com
License: BSD
Platform: any
Classifier: Development Status :: 4 - Beta
Classifier: Framework :: Flask
Classifier: Environment :: Web Environment
Classifier: Intended Audience :: Developers
Classifier: License :: OSI Approved :: BSD License
Classifier: Operating System :: OS Independent
Classifier: Programming Language :: Python :: 2.7
Classifier: Programming Language :: Python :: 3.4
Classifier: Topic :: Internet :: WWW/HTTP :: Dynamic Content
Classifier: Topic :: Software Development :: Libraries :: Python Modules
